[
  {
    "type": "Feature",
    "properties": {
      "scalerank": 1,
      "natscale": 300,
      "labelrank": 1,
      "featurecla": "Populated place",
      "name": "San Francisco",
      "namepar": null,
      "namealt": "San Francisco-Oakland",
      "diffascii": 0,
      "nameascii": "San Francisco",
      "adm0cap": 0,
      "capalt": null,
      "capin": null,
      "worldcity": 1,
      "megacity": 1,
      "sov0name": "United States",
      "sov_a3": "USA",
      "adm0name": "United States of America",
      "adm0_a3": "USA",
      "adm1name": "California",
      "iso_a2": "US",
      "note": null,
      "latitude": 37.7400077505,
      "longitude": -122.459977663,
      "changed": 0,
      "namediff": 0,
      "diffnote": null,
      "pop_max": 3450000,
      "pop_min": 732072,
      "pop_other": 27400,
      "rank_max": 12,
      "rank_min": 11,
      "geonameid": 5391959,
      "meganame": "San Francisco-Oakland",
      "ls_name": "San Francisco1",
      "ls_match": 1,
      "checkme": 0,
      "min_zoom": 2.7
    },
    "bbox": [-122.417169, 37.769196, -122.417169, 37.769196],
    "geometry": { "type": "Point", "coordinates": [-122.417169, 37.769196] }
  },
  {
    "type": "Feature",
    "properties": {
      "scalerank": 1,
      "natscale": 300,
      "labelrank": 1,
      "featurecla": "Populated place",
      "name": "Chicago",
      "namepar": null,
      "namealt": null,
      "diffascii": 0,
      "nameascii": "Chicago",
      "adm0cap": 0,
      "capalt": null,
      "capin": null,
      "worldcity": 1,
      "megacity": 1,
      "sov0name": "United States",
      "sov_a3": "USA",
      "adm0name": "United States of America",
      "adm0_a3": "USA",
      "adm1name": "Illinois",
      "iso_a2": "US",
      "note": null,
      "latitude": 41.8299906607,
      "longitude": -87.7500549741,
      "changed": 0,
      "namediff": 0,
      "diffnote": null,
      "pop_max": 8990000,
      "pop_min": 2841952,
      "pop_other": 3635101,
      "rank_max": 13,
      "rank_min": 12,
      "geonameid": 4887398,
      "meganame": "Chicago",
      "ls_name": "Chicago",
      "ls_match": 1,
      "checkme": 0,
      "min_zoom": 3
    },
    "bbox": [-87.752001, 41.831937, -87.752001, 41.831937],
    "geometry": { "type": "Point", "coordinates": [-87.752001, 41.831937] }
  },
  {
    "type": "Feature",
    "properties": {
      "scalerank": 1,
      "natscale": 300,
      "labelrank": 2,
      "featurecla": "Populated place",
      "name": "Vancouver",
      "namepar": null,
      "namealt": null,
      "diffascii": 0,
      "nameascii": "Vancouver",
      "adm0cap": 0,
      "capalt": null,
      "capin": null,
      "worldcity": 0,
      "megacity": 1,
      "sov0name": "Canada",
      "sov_a3": "CAN",
      "adm0name": "Canada",
      "adm0_a3": "CAN",
      "adm1name": "British Columbia",
      "iso_a2": "CA",
      "note": null,
      "latitude": 49.2734165841,
      "longitude": -123.121644218,
      "changed": 5,
      "namediff": 0,
      "diffnote": "Changed scale rank.",
      "pop_max": 2313328,
      "pop_min": 603502,
      "pop_other": 482002,
      "rank_max": 12,
      "rank_min": 11,
      "geonameid": 6173331,
      "meganame": "Vancouver",
      "ls_name": "Vancouver2",
      "ls_match": 1,
      "checkme": 0,
      "min_zoom": 2.1
    },
    "bbox": [-123.12359, 49.275362, -123.12359, 49.275362],
    "geometry": { "type": "Point", "coordinates": [-123.12359, 49.275362] }
  },
  {
    "type": "Feature",
    "properties": {
      "scalerank": 0,
      "natscale": 600,
      "labelrank": 1,
      "featurecla": "Populated place",
      "name": "Los Angeles",
      "namepar": null,
      "namealt": "Los Angeles-Long Beach-Santa Ana",
      "diffascii": 0,
      "nameascii": "Los Angeles",
      "adm0cap": 0,
      "capalt": null,
      "capin": null,
      "worldcity": 1,
      "megacity": 1,
      "sov0name": "United States",
      "sov_a3": "USA",
      "adm0name": "United States of America",
      "adm0_a3": "USA",
      "adm1name": "California",
      "iso_a2": "US",
      "note": null,
      "latitude": 33.9899782502,
      "longitude": -118.179980511,
      "changed": 0,
      "namediff": 0,
      "diffnote": null,
      "pop_max": 12500000,
      "pop_min": 3694820,
      "pop_other": 142265,
      "rank_max": 14,
      "rank_min": 12,
      "geonameid": 5368361,
      "meganame": "Los Angeles-Long Beach-Santa Ana",
      "ls_name": "Los Angeles1",
      "ls_match": 1,
      "checkme": 0,
      "min_zoom": 2
    },
    "bbox": [-118.181926, 33.991924, -118.181926, 33.991924],
    "geometry": { "type": "Point", "coordinates": [-118.181926, 33.991924] }
  }
]
